dld_magnet/__init__.py
dld_magnet-1.0.6.dist-info/METADATA
dld_magnet-1.0.6.dist-info/WHEEL
dld_magnet-1.0.6.dist-info/entry_points.txt
dld_magnet-1.0.6.dist-info/RECORD
